jupyterlite_simple_cors_proxy/__init__.py
jupyterlite_simple_cors_proxy/cacheproxy.py
jupyterlite_simple_cors_proxy/fastf1_proxy.py
jupyterlite_simple_cors_proxy/proxy.py
jupyterlite_simple_cors_proxy-0.1.17.dist-info/licenses/LICENSE
jupyterlite_simple_cors_proxy-0.1.17.dist-info/METADATA
jupyterlite_simple_cors_proxy-0.1.17.dist-info/WHEEL
jupyterlite_simple_cors_proxy-0.1.17.dist-info/top_level.txt
jupyterlite_simple_cors_proxy-0.1.17.dist-info/RECORD
