Metadata-Version: 2.4
Name: jupyterlite-simple-cors-proxy
Version: 0.1.17
Summary: A simple CORS proxy utility with requests-like response
Home-page: https://github.com/innovationOUtside/jupyterlite-simple-cors-proxy
Author: Tony Hirst
Author-email: tony.hirst@gmail.com
Classifier: Programming Language :: Python :: 3
Classifier: License :: OSI Approved :: MIT License
Classifier: Operating System :: OS Independent
Requires-Python: >=3.8
License-File: LICENSE
Requires-Dist: requests
Dynamic: author
Dynamic: author-email
Dynamic: classifier
Dynamic: description
Dynamic: description-content-type
Dynamic: home-page
Dynamic: license-file
Dynamic: requires-dist
Dynamic: requires-python
Dynamic: summary
